{"cameraMode":{"drawMode":0,"name":"Shaded","section":"Shading Mode"},"sceneLighting":true,"audioPlay":false,"sceneViewState":{"m_AlwaysRefresh":false,"showFog":true,"showSkybox":true,"showFlares":true,"showImageEffects":true,"showParticleSystems":true,"showVisualEffectGraphs":true,"m_FxEnabled":true},"in2DMode":false,"pivot":{"x":-68.7344741821289,"y":-28.59435272216797,"z":-61.058570861816409},"rotation":{"x":0.04643677920103073,"y":-0.9441478252410889,"z":0.15169747173786164,"w":0.289013147354126},"size":60.504547119140628,"orthographic":false}