{"cameraMode":{"drawMode":0,"name":"Shaded","section":"Shading Mode"},"sceneLighting":true,"audioPlay":false,"sceneViewState":{"m_AlwaysRefresh":false,"showFog":true,"showSkybox":true,"showFlares":true,"showImageEffects":true,"showParticleSystems":true,"showVisualEffectGraphs":true,"m_FxEnabled":true},"in2DMode":false,"pivot":{"x":-40.78832244873047,"y":-12.58749771118164,"z":128.26910400390626},"rotation":{"x":0.12589526176452638,"y":-0.4119228720664978,"z":0.05771057680249214,"w":0.9008565545082092},"size":78.03609466552735,"orthographic":false}